pss_pywaapi.py
pss_helpers/AudioFileReader.py
pss_helpers/Files.py
pss_helpers/__init__.py
pss_helpers/gui.py
pss_helpers/soundbank_helper.py
pss_helpers/wwise_settings.py
pss_pywaapi-1.0.6.dist-info/LICENCE
pss_pywaapi-1.0.6.dist-info/METADATA
pss_pywaapi-1.0.6.dist-info/WHEEL
pss_pywaapi-1.0.6.dist-info/top_level.txt
pss_pywaapi-1.0.6.dist-info/RECORD
